README.rst
setup.cfg
setup.py
sphinxcontrib/__init__.py
sphinxcontrib/ansibleautodoc/__init__.py
sphinxcontrib/ansibleautodoc/ansibleautodoc.py
sphinxcontrib/ansibleautodoc/directives.py
sphinxcontrib/ansibleautodoc/i18n.py
sphinxcontrib_ansibleautodoc.egg-info/PKG-INFO
sphinxcontrib_ansibleautodoc.egg-info/SOURCES.txt
sphinxcontrib_ansibleautodoc.egg-info/dependency_links.txt
sphinxcontrib_ansibleautodoc.egg-info/namespace_packages.txt
sphinxcontrib_ansibleautodoc.egg-info/not-zip-safe
sphinxcontrib_ansibleautodoc.egg-info/pbr.json
sphinxcontrib_ansibleautodoc.egg-info/requires.txt
sphinxcontrib_ansibleautodoc.egg-info/top_level.txt