Metadata-Version: 1.1
Name: sphinxcontrib-ansibleautodoc
Version: 0.0.5
Summary: autodoc for ansible playbook
Home-page: http://github.com/shirou/sphinxcontrib-ansibleautodoc
Author: WAKAYAMA Shirou
Author-email: shirou.faw@gmail.com
License: BSD
Download-URL: http://pypi.python.org/pypi/sphinxcontrib-ansibleautodoc
Platform: any
Classifier: Development Status :: 4 - Beta
Classifier: Environment :: Console
Classifier: Intended Audience :: Developers
Classifier: License :: OSI Approved :: BSD License
Classifier: Operating System :: OS Independent
Classifier: Programming Language :: Python
Classifier: Topic :: Documentation
Classifier: Topic :: Utilities
